[
    {
        "startTime":"09:00 AM",
        "topic":"Registration",
        "tag":"",
        "des":"Lorem ipsum dolor sit amet consectetur, adipisicing elit. Magnam, aliquam! Fugiat, voluptate neque maxime, recusandae suscipit perspiciatis "
    },
    {
        "startTime":"10:00 AM",
        "topic":"Welcome Keynote",
        "tag":"",
        "des":"Lorem ipsum dolor sit amet consectetur, adipisicing elit. Magnam, aliquam! Fugiat, voluptate neque maxime, recusandae suscipit perspiciatis "
    },
    {
        "startTime":"10:30 AM",
        "topic":"Women Transition from campus to corporate",
        "tag":"",
        "des":"+"
    },
    {
        "startTime":"11:00 AM",
        "topic":"Fun Activities",
        "tag":"Fun",
        "des":"Let's enjoy a bit before we start writing some code."
    },
    {
        "startTime":"11:30 AM",
        "topic":"Firebase Web App Deployment",
        "tag":"Web",
        "des":""
    },
    {
        "startTime":"12:30 PM",
        "topic":"Activities [Success Stories]",
        "tag":"Fun",
        "des":""
    },
    {
        "startTime":"01:00 PM",
        "topic":"Lunch & Networking",
        "tag":"Food",
        "des":""
    },
    {
        "startTime":"02:30 PM",
        "topic":"I’m Remarkable",
        "tag":"Self Branding",
        "des":""
    },
    {
        "startTime":"03:30 PM",
        "topic":"Why I can’t?",
        "tag":"Self Branding",
        "des":""
    },
    {
        "startTime":"04:00 PM",
        "topic":"Fireside Lightning Talks",
        "tag":"",
        "des":""
    },
    {
        "startTime":"04:30 PM",
        "topic":"Closing Note",
        "tag":"",
        "des":""
    }

]
